lazytextpredict/__init__.py
lazytextpredict/basic_classification.py
lazytextpredict/example_code.py
lazy_text_predict-0.0.11.dist-info/LICENSE
lazy_text_predict-0.0.11.dist-info/METADATA
lazy_text_predict-0.0.11.dist-info/WHEEL
lazy_text_predict-0.0.11.dist-info/top_level.txt
lazy_text_predict-0.0.11.dist-info/RECORD
