Metadata-Version: 2.1
Name: lazy-text-predict
Version: 0.0.11
Summary: Text classification automl
Home-page: https://github.com/lemay-ai/lazyTextPredict
Author: Edward Booker
Author-email: epb378@gmail.com
License: UNKNOWN
Platform: UNKNOWN
Classifier: Programming Language :: Python :: 3
Classifier: License :: OSI Approved :: MIT License
Classifier: Operating System :: OS Independent
Classifier: Topic :: Scientific/Engineering :: Artificial Intelligence
Requires-Python: >=3.6
License-File: LICENSE
Requires-Dist: transformers
Requires-Dist: nlp
Requires-Dist: torch
Requires-Dist: numpy
Requires-Dist: scikit-learn
Requires-Dist: sentencepiece
